pyritofile/__init__.py
pyritofile/anm.py
pyritofile/bin.py
pyritofile/bnk.py
pyritofile/ermmm.py
pyritofile/mapgeo.py
pyritofile/rst.py
pyritofile/skl.py
pyritofile/skn.py
pyritofile/so.py
pyritofile/stream.py
pyritofile/structs.py
pyritofile/tex.py
pyritofile/wad.py
pyritofile/wpk.py
pyritofile-0.2.5.dist-info/licenses/LICENSE.txt
pyritofile-0.2.5.dist-info/METADATA
pyritofile-0.2.5.dist-info/WHEEL
pyritofile-0.2.5.dist-info/top_level.txt
pyritofile-0.2.5.dist-info/RECORD
