Metadata-Version: 2.4
Name: pyritofile
Version: 0.2.5
Summary: Python package to deal with League of Legends files.
Author-email: GuiSaiUwU <contaguardian@gmail.com>
License: GPLv3+
Project-URL: Homepage, https://github.com/GuiSaiUwU/pyritofile-package
License-File: LICENSE.txt
Requires-Dist: xxhash>=3.5.0
Requires-Dist: pyzstd>=0.16.2
Dynamic: license-file
